{
"type": "FeatureCollection",
"name": "Pendidikan",
"crs": { "type": "name", "properties": { "name": "urn:ogc:def:crs:OGC:1.3:CRS84" } },
"features": [
{ "type": "Feature", "properties": { "NAMOBJ": "SMP Al Azhar 3 Wayhalim Lampung", "LUAS": 0.0, "KATPDK": 0, "JLPDDK": 0, "FGGPDK": 3, "REMARK": "Pendidikan Menengah Pertama", "FCODE": null, "SRS_ID": null, "LCODE": "GE0020", "METADATA": null, "JJGPDF": 2, "JNSPDL": 0 }, "geometry": { "type": "Point", "coordinates": [ 105.274130993000085, -5.378331494999941, 0.062999999994645 ] } },
{ "type": "Feature", "properties": { "NAMOBJ": "SMK Pelayaran Satria Bahari", "LUAS": 0.0, "KATPDK": 0, "JLPDDK": 0, "FGGPDK": 2, "REMARK": "Pendidikan Menengah Umum", "FCODE": null, "SRS_ID": null, "LCODE": "GE0020", "METADATA": null, "JJGPDF": 2, "JNSPDL": 0 }, "geometry": { "type": "Point", "coordinates": [ 105.274546161000046, -5.390928062999933, 0.0 ] } },
{ "type": "Feature", "properties": { "NAMOBJ": "SMP Xaverius 4", "LUAS": 0.0, "KATPDK": 0, "JLPDDK": 0, "FGGPDK": 3, "REMARK": "Pendidikan Menengah Pertama", "FCODE": null, "SRS_ID": null, "LCODE": "GE0020", "METADATA": null, "JJGPDF": 2, "JNSPDL": 0 }, "geometry": { "type": "Point", "coordinates": [ 105.279058987000042, -5.385645618999945, 0.0 ] } },
{ "type": "Feature", "properties": { "NAMOBJ": "Institut Satu Maret Bandarlampung", "LUAS": 0.0, "KATPDK": 0, "JLPDDK": 0, "FGGPDK": 1, "REMARK": "Pendidikan Tinggi", "FCODE": null, "SRS_ID": null, "LCODE": "GE0020", "METADATA": null, "JJGPDF": 3, "JNSPDL": 0 }, "geometry": { "type": "Point", "coordinates": [ 105.279281322000088, -5.382937930999958, 0.0 ] } },
{ "type": "Feature", "properties": { "NAMOBJ": "TPA Al Mukarromah", "LUAS": 0.0, "KATPDK": 0, "JLPDDK": 0, "FGGPDK": 10, "REMARK": "Pendidikan Keagamaan", "FCODE": null, "SRS_ID": null, "LCODE": "GE0020", "METADATA": null, "JJGPDF": 999, "JNSPDL": 0 }, "geometry": { "type": "Point", "coordinates": [ 105.269135087000052, -5.401614292999966, 103.631999999997788 ] } },
{ "type": "Feature", "properties": { "NAMOBJ": "SMA Tunas Mekar Indonesia", "LUAS": 0.0, "KATPDK": 0, "JLPDDK": 0, "FGGPDK": 2, "REMARK": "Pendidikan Menengah Umum", "FCODE": null, "SRS_ID": null, "LCODE": "GE0020", "METADATA": null, "JJGPDF": 2, "JNSPDL": 0 }, "geometry": { "type": "Point", "coordinates": [ 105.281856964000042, -5.399985337999965, 0.0 ] } },
{ "type": "Feature", "properties": { "NAMOBJ": "SMP Tunas Mekar Indonesia", "LUAS": 0.0, "KATPDK": 0, "JLPDDK": 0, "FGGPDK": 3, "REMARK": "Pendidikan Menengah Pertama", "FCODE": null, "SRS_ID": null, "LCODE": "GE0020", "METADATA": null, "JJGPDF": 2, "JNSPDL": 0 }, "geometry": { "type": "Point", "coordinates": [ 105.281849190000059, -5.399924814999963, 0.0 ] } },
{ "type": "Feature", "properties": { "NAMOBJ": "Sekolah Khusus & Terapi Growing Hope", "LUAS": 0.0, "KATPDK": 0, "JLPDDK": 0, "FGGPDK": 999, "REMARK": "Pendidikan/Penelitian Lainnya", "FCODE": null, "SRS_ID": null, "LCODE": "GE0020", "METADATA": null, "JJGPDF": 999, "JNSPDL": 0 }, "geometry": { "type": "Point", "coordinates": [ 105.271733274000042, -5.398392613999931, 101.802999999999884 ] } },
{ "type": "Feature", "properties": { "NAMOBJ": "SMK Negeri 1 Bandarlampung", "LUAS": 0.0, "KATPDK": 0, "JLPDDK": 0, "FGGPDK": 2, "REMARK": "Pendidikan Menengah Umum", "FCODE": null, "SRS_ID": null, "LCODE": "GE0020", "METADATA": null, "JJGPDF": 2, "JNSPDL": 0 }, "geometry": { "type": "Point", "coordinates": [ 105.278618240000071, -5.393594901999961, 101.498000000006869 ] } },
{ "type": "Feature", "properties": { "NAMOBJ": "SMK Dwi Pangga", "LUAS": 0.0, "KATPDK": 0, "JLPDDK": 0, "FGGPDK": 2, "REMARK": "Pendidikan Menengah Umum", "FCODE": null, "SRS_ID": null, "LCODE": "GE0020", "METADATA": null, "JJGPDF": 2, "JNSPDL": 0 }, "geometry": { "type": "Point", "coordinates": [ 105.265783526000064, -5.395319464999943, 118.262000000002445 ] } },
{ "type": "Feature", "properties": { "NAMOBJ": "SMP Dwi Pangga", "LUAS": 0.0, "KATPDK": 0, "JLPDDK": 0, "FGGPDK": 3, "REMARK": "Pendidikan Menengah Pertama", "FCODE": null, "SRS_ID": null, "LCODE": "GE0020", "METADATA": null, "JJGPDF": 2, "JNSPDL": 0 }, "geometry": { "type": "Point", "coordinates": [ 105.265790113000037, -5.395225951999976, -269.737999999997555 ] } },
{ "type": "Feature", "properties": { "NAMOBJ": "TPA Nurul Ikhsan", "LUAS": 0.0, "KATPDK": 0, "JLPDDK": 0, "FGGPDK": 10, "REMARK": "Pendidikan Keagamaan", "FCODE": null, "SRS_ID": null, "LCODE": "GE0020", "METADATA": null, "JJGPDF": 999, "JNSPDL": 0 }, "geometry": { "type": "Point", "coordinates": [ 105.262238738000065, -5.401318777999961, 108.203999999997905 ] } },
{ "type": "Feature", "properties": { "NAMOBJ": "TPA Al Atsar", "LUAS": 0.0, "KATPDK": 0, "JLPDDK": 0, "FGGPDK": 10, "REMARK": "Pendidikan Keagamaan", "FCODE": null, "SRS_ID": null, "LCODE": "GE0020", "METADATA": null, "JJGPDF": 999, "JNSPDL": 0 }, "geometry": { "type": "Point", "coordinates": [ 105.267549308000071, -5.399577786999942, 110.947000000000116 ] } }
]
}
